voice_Modem_Testing/__init__.py
voice_Modem_Testing-0.4.dist-info/LICENSE.txt
voice_Modem_Testing-0.4.dist-info/METADATA
voice_Modem_Testing-0.4.dist-info/WHEEL
voice_Modem_Testing-0.4.dist-info/top_level.txt
voice_Modem_Testing-0.4.dist-info/RECORD
