Metadata-Version: 2.1
Name: voice-Modem-Testing
Version: 0.4
Summary: This is a voice modem testing through raspberry
Home-page: UNKNOWN
Author: Abirami
Author-email: abiramig1930@gmail.com
License: UNKNOWN
Platform: UNKNOWN
Classifier: Programming Language :: Python :: 3
Classifier: License :: OSI Approved :: MIT License
Classifier: Operating System :: OS Independent
License-File: LICENSE.txt
